simple_health_check/__init__.py
simple_health_check/apps.py
simple_health_check/exceptions.py
simple_health_check/models.py
simple_health_check/settings.py
simple_health_check/tests.py
simple_health_check/urls.py
simple_health_check/views.py
simple_health_check/checks/__init__.py
simple_health_check/checks/caches.py
simple_health_check/checks/db.py
simple_health_check/checks/dummy.py
simple_health_check/checks/migrations.py
simple_health_check/checks/ps.py
simple_health_check/migrations/__init__.py
django_simple_health_check-0.6.1.dist-info/LICENSE
django_simple_health_check-0.6.1.dist-info/METADATA
django_simple_health_check-0.6.1.dist-info/WHEEL
django_simple_health_check-0.6.1.dist-info/top_level.txt
django_simple_health_check-0.6.1.dist-info/RECORD
