Metadata-Version: 2.1
Name: django-simple-health-check
Version: 0.6.1
Summary: Simple Django health check
Home-page: https://github.com/pikhovkin/django-simple-health-check
Author: Sergei Pikhovkin
Author-email: s@pikhovkin.ru
License: MIT
Keywords: django,monitoring,healthcheck,health-check,ping,health-checks,healthchecks,liveness,readiness,liveness-detection,readiness-checker,django-health-check,readiness-detection,liveness-checker
Classifier: Development Status :: 3 - Alpha
Classifier: Environment :: Web Environment
Classifier: Framework :: Django :: 3.1
Classifier: Framework :: Django :: 3.2
Classifier: Framework :: Django :: 4.0
Classifier: Framework :: Django :: 4.1
Classifier: Framework :: Django :: 4.2
Classifier: Framework :: Django :: 5.0
Classifier: Intended Audience :: Developers
Classifier: License :: OSI Approved :: MIT License
Classifier: Operating System :: OS Independent
Classifier: Programming Language :: Python :: 3 :: Only
Classifier: Programming Language :: Python :: 3.7
Classifier: Programming Language :: Python :: 3.8
Classifier: Programming Language :: Python :: 3.9
Classifier: Programming Language :: Python :: 3.10
Classifier: Programming Language :: Python :: 3.11
Requires-Python: >=3.7,<4.0
License-File: LICENSE
Requires-Dist: Django <5.1,>=3.1
Provides-Extra: psutil
Requires-Dist: psutil ; extra == 'psutil'
